lowhaio.py
lowhaio-0.0.89.dist-info/LICENSE
lowhaio-0.0.89.dist-info/METADATA
lowhaio-0.0.89.dist-info/WHEEL
lowhaio-0.0.89.dist-info/top_level.txt
lowhaio-0.0.89.dist-info/RECORD
