Metadata-Version: 2.1
Name: lowhaio
Version: 0.0.89
Summary: Lightweight Python asyncio HTTP client
Home-page: https://github.com/michalc/lowhaio
Author: Michal Charemza
Author-email: michal@charemza.name
Keywords: http/1.1
Classifier: Programming Language :: Python :: 3
Classifier: License :: OSI Approved :: MIT License
Classifier: Operating System :: OS Independent
Classifier: Framework :: AsyncIO
Requires-Python: >=3.6.3
License-File: LICENSE
Requires-Dist: aiodnsresolver >=0.0.149
